setup.py
exlist/__init__.py
exlist/exlist.py
exlist.egg-info/PKG-INFO
exlist.egg-info/SOURCES.txt
exlist.egg-info/dependency_links.txt
exlist.egg-info/top_level.txt