Metadata-Version: 1.0
Name: exlist
Version: 0.5
Summary: Enable to use method chain on list
Home-page: https://github.com/orion46/exlist.git
Author: orion46
Author-email: earth.nobu.light@gmail.com
License: MIT
Keywords: list
Platform: UNKNOWN
